{"guide_function-binding.md":"fa8942ae","guide_faq.md":"7fbc745d","guide_error-handling.md":"660d8691","guide_class-binding.md":"2b78bcae","guide_getting-started.md":"c9cb5a6e","guide_index.md":"8111fe47","guide_modularization.md":"572722b3","guide_tsfn.md":"22437663","guide_using-cmake.md":"13c4dd86","guide_using-cpp.md":"b45c316f","guide_using-rust.md":"8af4da17","index.md":"f1240cf7","reference_additional.md":"91c1b9ec","zh_guide_class-binding.md":"8c4852e5","zh_guide_function-binding.md":"cd5c6191","zh_guide_index.md":"73d9e36d","zh_guide_modularization.md":"b8f76f1b","zh_guide_multithreaded-async.md":"39482328","zh_guide_using-cpp.md":"b2d6fb6e","zh_index.md":"e4ea2542","zh_reference_additional.md":"ef41b620","zh_reference_list.md":"0e4fa8d8","zh_guide_getting-started.md":"b76993f0","zh_guide_tsfn.md":"85079e27","zh_guide_using-rust.md":"822562ed","reference_list.md":"d2d2142a","zh_guide_using-cmake.md":"00d8ee07","zh_guide_error-handling.md":"3ba666a8","zh_guide_faq.md":"4dd9b725","guide_multithreaded-async.md":"a49ca629"}
